{
  "name": "Col_PirateMark",
  "asset": "assets/sprites/Col_PirateMark.png",
  "frame_w": 16,
  "frame_h": 16,
  "preview_palette": "Microsoft Windows 16",
  "own_palette": [
    26620,
    4192,
    14096
  ],
  "compress_method": "median_cut",
  "states": [
    {
      "name": "Idle",
      "speed": 8,
      "loop": true,
      "directions": [
        {
          "dir": 7,
          "frames": [
            {
              "tiles": []
            }
          ],
          "flip_h": true,
          "mirror_of": 3
        },
        {
          "dir": 0,
          "frames": [
            {
              "tiles": [
                {
                  "src_col": 0,
                  "src_row": 0,
                  "dst_col": 0,
                  "dst_row": 0
                },
                {
                  "src_col": 1,
                  "src_row": 0,
                  "dst_col": 1,
                  "dst_row": 0
                },
                {
                  "src_col": 0,
                  "src_row": 1,
                  "dst_col": 0,
                  "dst_row": 1
                },
                {
                  "src_col": 1,
                  "src_row": 1,
                  "dst_col": 1,
                  "dst_row": 1
                }
              ]
            },
            {
              "tiles": [
                {
                  "src_col": 2,
                  "src_row": 0,
                  "dst_col": 0,
                  "dst_row": 0
                },
                {
                  "src_col": 3,
                  "src_row": 0,
                  "dst_col": 1,
                  "dst_row": 0
                },
                {
                  "src_col": 2,
                  "src_row": 1,
                  "dst_col": 0,
                  "dst_row": 1
                },
                {
                  "src_col": 3,
                  "src_row": 1,
                  "dst_col": 1,
                  "dst_row": 1
                }
              ]
            },
            {
              "tiles": [
                {
                  "src_col": 4,
                  "src_row": 0,
                  "dst_col": 0,
                  "dst_row": 0
                },
                {
                  "src_col": 5,
                  "src_row": 0,
                  "dst_col": 1,
                  "dst_row": 0
                },
                {
                  "src_col": 4,
                  "src_row": 1,
                  "dst_col": 0,
                  "dst_row": 1
                },
                {
                  "src_col": 5,
                  "src_row": 1,
                  "dst_col": 1,
                  "dst_row": 1
                }
              ]
            },
            {
              "tiles": [
                {
                  "src_col": 2,
                  "src_row": 0,
                  "dst_col": 0,
                  "dst_row": 0
                },
                {
                  "src_col": 3,
                  "src_row": 0,
                  "dst_col": 1,
                  "dst_row": 0
                },
                {
                  "src_col": 2,
                  "src_row": 1,
                  "dst_col": 0,
                  "dst_row": 1
                },
                {
                  "src_col": 3,
                  "src_row": 1,
                  "dst_col": 1,
                  "dst_row": 1
                }
              ]
            }
          ]
        },
        {
          "dir": 3,
          "frames": [
            {
              "tiles": [
                {
                  "src_col": 0,
                  "src_row": 0,
                  "dst_col": 0,
                  "dst_row": 0
                },
                {
                  "src_col": 1,
                  "src_row": 0,
                  "dst_col": 1,
                  "dst_row": 0
                },
                {
                  "src_col": 0,
                  "src_row": 1,
                  "dst_col": 0,
                  "dst_row": 1
                },
                {
                  "src_col": 1,
                  "src_row": 1,
                  "dst_col": 1,
                  "dst_row": 1
                }
              ]
            },
            {
              "tiles": [
                {
                  "src_col": 2,
                  "src_row": 0,
                  "dst_col": 0,
                  "dst_row": 0
                },
                {
                  "src_col": 3,
                  "src_row": 0,
                  "dst_col": 1,
                  "dst_row": 0
                },
                {
                  "src_col": 2,
                  "src_row": 1,
                  "dst_col": 0,
                  "dst_row": 1
                },
                {
                  "src_col": 3,
                  "src_row": 1,
                  "dst_col": 1,
                  "dst_row": 1
                }
              ]
            },
            {
              "tiles": [
                {
                  "src_col": 4,
                  "src_row": 0,
                  "dst_col": 0,
                  "dst_row": 0
                },
                {
                  "src_col": 5,
                  "src_row": 0,
                  "dst_col": 1,
                  "dst_row": 0
                },
                {
                  "src_col": 4,
                  "src_row": 1,
                  "dst_col": 0,
                  "dst_row": 1
                },
                {
                  "src_col": 5,
                  "src_row": 1,
                  "dst_col": 1,
                  "dst_row": 1
                }
              ]
            },
            {
              "tiles": [
                {
                  "src_col": 2,
                  "src_row": 0,
                  "dst_col": 0,
                  "dst_row": 0
                },
                {
                  "src_col": 3,
                  "src_row": 0,
                  "dst_col": 1,
                  "dst_row": 0
                },
                {
                  "src_col": 2,
                  "src_row": 1,
                  "dst_col": 0,
                  "dst_row": 1
                },
                {
                  "src_col": 3,
                  "src_row": 1,
                  "dst_col": 1,
                  "dst_row": 1
                }
              ]
            }
          ]
        }
      ]
    }
  ]
}